tax2proteome/Accession.py
tax2proteome/DatabaseCleaner.py
tax2proteome/Download.py
tax2proteome/Output.py
tax2proteome/TaxonGraph.py
tax2proteome/TestFile.py
tax2proteome/WriteCustomDB.py
tax2proteome/__init__.py
tax2proteome/__main__.py
tax2proteome/version.py
tax2proteome-0.0.1.dist-info/LICENSE
tax2proteome-0.0.1.dist-info/METADATA
tax2proteome-0.0.1.dist-info/WHEEL
tax2proteome-0.0.1.dist-info/top_level.txt
tax2proteome-0.0.1.dist-info/RECORD
